napari_ehooke/__init__.py
napari_ehooke/_computecells.py
napari_ehooke/_computefeatures.py
napari_ehooke/_computemask.py
napari_ehooke/_filtercells.py
napari_ehooke/_sample_data.py
napari_ehooke/napari.yaml
napari_ehooke/_tests/__init__.py
napari_ehooke/_tests/test_sample_data.py
napari_ehooke/ehooke/__init__.py
napari_ehooke/ehooke/cellaverager.py
napari_ehooke/ehooke/cellcycleclassifier.py
napari_ehooke/ehooke/cellprocessing.py
napari_ehooke/ehooke/cells.py
napari_ehooke/ehooke/colocmanager.py
napari_ehooke/ehooke/mask.py
napari_ehooke/ehooke/reports.py
napari_ehooke/ehooke/segments.py
napari_ehooke-0.0.17.dist-info/LICENSE
napari_ehooke-0.0.17.dist-info/METADATA
napari_ehooke-0.0.17.dist-info/WHEEL
napari_ehooke-0.0.17.dist-info/entry_points.txt
napari_ehooke-0.0.17.dist-info/top_level.txt
napari_ehooke-0.0.17.dist-info/RECORD
