Metadata-Version: 2.2
Name: napari-ehooke
Version: 0.0.17
Summary: eHooke implementation within napari
Home-page: https://github.com/antmsbrito/napari-ehooke
Author: António Brito
Author-email: antmsbrito95@gmail.com
License: BSD-3-Clause
Project-URL: Bug Tracker, https://github.com/antmsbrito/napari-ehooke/issues
Project-URL: Documentation, https://github.com/antmsbrito/napari-ehooke#README.md
Project-URL: Source Code, https://github.com/antmsbrito/napari-ehooke
Project-URL: User Support, https://github.com/antmsbrito/napari-ehooke/issues
Classifier: Development Status :: 2 - Pre-Alpha
Classifier: Framework :: napari
Classifier: Intended Audience :: Developers
Classifier: License :: OSI Approved :: BSD License
Classifier: Operating System :: OS Independent
Classifier: Programming Language :: Python
Classifier: Programming Language :: Python :: 3
Classifier: Programming Language :: Python :: 3 :: Only
Classifier: Programming Language :: Python :: 3.8
Classifier: Programming Language :: Python :: 3.9
Classifier: Programming Language :: Python :: 3.10
Classifier: Topic :: Scientific/Engineering :: Image Processing
Requires-Python: >=3.8
License-File: LICENSE
Requires-Dist: numpy<2.0
Requires-Dist: magicgui==0.6.1
Requires-Dist: napari[all]
Requires-Dist: tensorflow<=2.15.0
Requires-Dist: napari-skimage-regionprops
Requires-Dist: stardist-napari==2022.12.6
Requires-Dist: scikit-learn
Requires-Dist: scikit-image==0.20.0
Requires-Dist: pandas
Provides-Extra: testing
Requires-Dist: tox; extra == "testing"
Requires-Dist: pytest; extra == "testing"
Requires-Dist: pytest-cov; extra == "testing"
Requires-Dist: pytest-qt; extra == "testing"
Requires-Dist: napari; extra == "testing"
Requires-Dist: pyqt5; extra == "testing"
